{"restaurant": {"has_online_delivery": 0, "photos_url": "https://www.zomato.com/spicecaves/photos?utm_source=api_basic_user&utm_medium=api&utm_campaign=v2.1#tabtop", "url": "https://www.zomato.com/spicecaves?utm_source=api_basic_user&utm_medium=api&utm_campaign=v2.1", "price_range": 3, "apikey": "b90e6a8c738410315a20c449fe2eb1b1", "user_rating": {"rating_text": "Very Good", "rating_color": "5BA829", "votes": "691", "aggregate_rating": "4.2"}, "deeplink": "zomato://restaurant/801170", "name": "Spice Caves", "has_table_booking": 0, "is_delivering_now": 0, "R": {"res_id": 801170}, "menu_url": "https://www.zomato.com/spicecaves/menu?utm_source=api_basic_user&utm_medium=api&utm_campaign=v2.1&openSwipeBox=menu&showMinimal=1#tabtop", "average_cost_for_two": 1200, "switch_to_order_menu": 0, "offers": [], "cuisines": "North Indian, Chinese, Mughlai", "location": {"longitude": "80.9988571509", "latitude": "26.8533839458", "address": "Above Samsung TV Showroom, Patrakar Puram, Gomti Nagar, Lucknow", "city": "Lucknow", "country_id": 1, "locality_verbose": "Gomti Nagar, Lucknow", "city_id": 8, "zipcode": "", "locality": "Gomti Nagar"}, "featured_image": "https://b.zmtcdn.com/data/pictures/0/801170/8eb07cb90603c089b132070868f3b203_featured_v2.jpg", "zomato_events": [{"event": {"display_date": "01 April - 04 May", "end_time": "23:59:59", "date_added": "2017-03-14 21:02:50", "start_date": "2017-04-01", "photos": [{"photo": {"photo_id": 180169, "order": 0, "thumb_url": "https://b.zmtcdn.com/data/zomato_events/photos/9f1/b158ff0a33fe15cd61f5133ad0e9a9f1_1485989943.jpg?fit=around%7C100%3A100&crop=100%3A100%3B%2A%2C%2A", "url": "https://b.zmtcdn.com/data/zomato_events/photos/9f1/b158ff0a33fe15cd61f5133ad0e9a9f1_1485989943.jpg", "md5sum": "b158ff0a33fe15cd61f5133ad0e9a9f1", "uuid": 5569632848, "type": "FEATURED"}}, {"photo": {"photo_id": 180170, "order": 1, "thumb_url": "https://b.zmtcdn.com/data/zomato_events/photos/274/546722195093092072c8c401b2658274_1468952039.jpg?fit=around%7C100%3A100&crop=100%3A100%3B%2A%2C%2A", "url": "https://b.zmtcdn.com/data/zomato_events/photos/274/546722195093092072c8c401b2658274_1468952039.jpg", "md5sum": "546722195093092072c8c401b2658274", "uuid": 5569632891, "type": "FEATURED"}}, {"photo": {"photo_id": 180171, "order": 2, "thumb_url": "https://b.zmtcdn.com/data/zomato_events/photos/190/f412887a46497584625f91c6f4e44190_1468950513.jpg?fit=around%7C100%3A100&crop=100%3A100%3B%2A%2C%2A", "url": "https://b.zmtcdn.com/data/zomato_events/photos/190/f412887a46497584625f91c6f4e44190_1468950513.jpg", "md5sum": "f412887a46497584625f91c6f4e44190", "uuid": 5569632189, "type": "FEATURED"}}, {"photo": {"photo_id": 180172, "order": 3, "thumb_url": "https://b.zmtcdn.com/data/zomato_events/photos/0d8/72150d6c9f0ddc96d839d3956c62d0d8_1468950513.jpg?fit=around%7C100%3A100&crop=100%3A100%3B%2A%2C%2A", "url": "https://b.zmtcdn.com/data/zomato_events/photos/0d8/72150d6c9f0ddc96d839d3956c62d0d8_1468950513.jpg", "md5sum": "72150d6c9f0ddc96d839d3956c62d0d8", "uuid": 5569632377, "type": "NORMAL"}}, {"photo": {"photo_id": 180173, "order": 4, "thumb_url": "https://b.zmtcdn.com/data/zomato_events/photos/9ae/75549105d94a4485548ae6e190e479ae_1468952039.jpg?fit=around%7C100%3A100&crop=100%3A100%3B%2A%2C%2A", "url": "https://b.zmtcdn.com/data/zomato_events/photos/9ae/75549105d94a4485548ae6e190e479ae_1468952039.jpg", "md5sum": "75549105d94a4485548ae6e190e479ae", "uuid": 5569632104, "type": "NORMAL"}}, {"photo": {"photo_id": 180174, "order": 5, "thumb_url": "https://b.zmtcdn.com/data/zomato_events/photos/8c6/1ea5a2c9decf2aa11e0aa30a006748c6_1485989944.jpg?fit=around%7C100%3A100&crop=100%3A100%3B%2A%2C%2A", "url": "https://b.zmtcdn.com/data/zomato_events/photos/8c6/1ea5a2c9decf2aa11e0aa30a006748c6_1485989944.jpg", "md5sum": "1ea5a2c9decf2aa11e0aa30a006748c6", "uuid": 5569632148, "type": "NORMAL"}}], "share_url": "http://www.zoma.to/r/801170", "description": "Spice Caves invites you to celebrate your birthday like never before. With magic candles, balloon decoration, choice of music, staff surprise celebration and dslr photography complementary from our side, it's surely gonna be a grand celebration. Go Spica! ", "title": "#BIRTHDAY #DESTINATION ", "display_time": "11:00 am onwards", "book_link": "", "restaurants": [], "disclaimer": "Restaurants are solely responsible for the service; availability and quality of the events including all or any cancellations/ modifications/ complaints.", "friendly_start_date": "01 April", "is_end_time_set": 0, "event_id": 113652, "end_date": "2017-05-04", "event_category": 1, "friendly_end_date": "04 May", "is_active": 1, "start_time": "11:00:00", "is_valid": 1, "event_category_name": ""}}], "currency": "Rs.", "id": "801170", "thumb": "https://b.zmtcdn.com/data/pictures/0/801170/8eb07cb90603c089b132070868f3b203_featured_v2.jpg", "establishment_types": [], "events_url": "https://www.zomato.com/spicecaves/events#tabtop?utm_source=api_basic_user&utm_medium=api&utm_campaign=v2.1"}}