{"restaurant": {"has_online_delivery": 1, "photos_url": "https://www.zomato.com/pune/blue-water-ravet/photos?utm_source=api_basic_user&utm_medium=api&utm_campaign=v2.1#tabtop", "url": "https://www.zomato.com/pune/blue-water-ravet?utm_source=api_basic_user&utm_medium=api&utm_campaign=v2.1", "price_range": 3, "apikey": "b90e6a8c738410315a20c449fe2eb1b1", "user_rating": {"rating_text": "Very Good", "rating_color": "5BA829", "votes": "487", "aggregate_rating": "4.2"}, "deeplink": "zomato://restaurant/18292672", "name": "Blue Water", "has_table_booking": 1, "is_delivering_now": 0, "R": {"res_id": 18292672}, "menu_url": "https://www.zomato.com/pune/blue-water-ravet/menu?utm_source=api_basic_user&utm_medium=api&utm_campaign=v2.1&openSwipeBox=menu&showMinimal=1#tabtop", "average_cost_for_two": 1500, "book_url": "https://www.zomato.com/pune/blue-water-ravet/book?utm_source=api_basic_user&utm_medium=api&utm_campaign=v2.1", "switch_to_order_menu": 0, "offers": [], "cuisines": "North Indian, Chinese, Continental", "location": {"longitude": "73.7510812283", "latitude": "18.6362151260", "address": "Punawale, Near Basket Bridge,Off Aundh-Ravet BRT, Ravet, Pune", "city": "Pune", "country_id": 1, "locality_verbose": "Ravet, Pune", "city_id": 5, "zipcode": "", "locality": "Ravet"}, "featured_image": "https://b.zmtcdn.com/data/pictures/2/18292672/f6245adacb8918a11813b4d0c4b20609_featured_v2.jpg", "zomato_events": [{"event": {"display_date": "16 April", "end_time": "22:00:00", "date_added": "2017-04-15 19:02:12", "start_date": "2017-04-16", "photos": [{"photo": {"photo_id": 189193, "order": 0, "thumb_url": "https://b.zmtcdn.com/data/zomato_events/photos/a21/448a31c91829cde29bfbf47e1c62fa21_1492263132.jpg?fit=around%7C100%3A100&crop=100%3A100%3B%2A%2C%2A", "url": "https://b.zmtcdn.com/data/zomato_events/photos/a21/448a31c91829cde29bfbf47e1c62fa21_1492263132.jpg", "md5sum": "448a31c91829cde29bfbf47e1c62fa21", "uuid": 1492263128216940, "type": "NORMAL"}}], "share_url": "http://www.zoma.to/r/18292672", "description": "Raiez Khan is back to mesmerize our patrons. Come by and watch him live from 8 PM onward. Have a fantastic weekend! \r\nCall for bookings ?: +91 7276 676644. Book Now! \r\n~\r\n#SundayNightLive #BlueWater #Zomato #Pune #BOGO", "title": "Sunday Night Live ", "display_time": "08:00 pm - 10:00 pm", "book_link": "", "restaurants": [], "disclaimer": "Restaurants are solely responsible for the service; availability and quality of the events including all or any cancellations/ modifications/ complaints.", "friendly_start_date": "16 April", "is_end_time_set": 1, "event_id": 120530, "end_date": "2017-04-16", "event_category": 0, "friendly_end_date": "16 April", "is_active": 1, "start_time": "20:00:00", "is_valid": 1, "event_category_name": ""}}], "currency": "Rs.", "id": "18292672", "thumb": "https://b.zmtcdn.com/data/pictures/2/18292672/f6245adacb8918a11813b4d0c4b20609_featured_v2.jpg", "establishment_types": [], "events_url": "https://www.zomato.com/pune/blue-water-ravet/events#tabtop?utm_source=api_basic_user&utm_medium=api&utm_campaign=v2.1"}}