{"restaurant": {"has_online_delivery": 0, "photos_url": "https://www.zomato.com/ncr/niche-cafe-bar-connaught-place-new-delhi/photos?utm_source=api_basic_user&utm_medium=api&utm_campaign=v2.1#tabtop", "url": "https://www.zomato.com/ncr/niche-cafe-bar-connaught-place-new-delhi?utm_source=api_basic_user&utm_medium=api&utm_campaign=v2.1", "price_range": 3, "apikey": "9421941dbc9358a88376f2ee33bbb06c", "user_rating": {"rating_text": "Very Good", "rating_color": "5BA829", "votes": "492", "aggregate_rating": "4.1"}, "R": {"res_id": 18222559}, "name": "{Niche} - Cafe & Bar", "cuisines": "North Indian, Chinese, Italian, Continental", "is_delivering_now": 0, "deeplink": "zomato://restaurant/18222559", "menu_url": "https://www.zomato.com/ncr/niche-cafe-bar-connaught-place-new-delhi/menu?utm_source=api_basic_user&utm_medium=api&utm_campaign=v2.1&openSwipeBox=menu&showMinimal=1#tabtop", "average_cost_for_two": 1500, "book_url": "https://www.zomato.com/ncr/niche-cafe-bar-connaught-place-new-delhi/book?utm_source=api_basic_user&utm_medium=api&utm_campaign=v2.1", "switch_to_order_menu": 0, "offers": [], "has_table_booking": 1, "location": {"latitude": "28.6315156000", "address": "2nd & 3rd Floor, M-16, M Block, Outer Circle, Connaught Place, New Delhi", "city": "New Delhi", "country_id": 1, "locality_verbose": "Connaught Place, New Delhi", "city_id": 1, "zipcode": "", "longitude": "77.2225074000", "locality": "Connaught Place"}, "featured_image": "https://b.zmtcdn.com/data/pictures/9/18222559/f3b1c0e0901083619784bf0ba7c25996_featured_v2.jpg", "zomato_events": [{"event": {"display_date": "02 March - 30 June", "end_time": "20:00:00", "date_added": "2017-03-02 19:44:08", "start_date": "2017-03-02", "photos": [{"photo": {"photo_id": 176933, "order": 0, "type": "NORMAL", "url": "https://b.zmtcdn.com/data/zomato_events/photos/939/feba140f129f3075374be016891c3939_1488464048.jpg", "md5sum": "feba140f129f3075374be016891c3939", "uuid": 1488463982176812, "thumb_url": "https://b.zmtcdn.com/data/zomato_events/photos/939/feba140f129f3075374be016891c3939_1488464048.jpg?fit=around%7C100%3A100&crop=100%3A100%3B%2A%2C%2A"}}], "share_url": "http://www.zoma.to/r/18222559", "description": "Imagine a long chat and droplets trickling down your chilled beers and by the end of it is an end of your happy hour? Isn't much of a good thought right? Niche is extending its happy hours to allow you to have the longest chat with the most chilled beers to set your mood to higher spirits! Why limit happy to an hour?", "title": "Why limit happy to an hour?", "display_time": "04:00 pm - 08:00 pm", "book_link": "", "restaurants": [], "disclaimer": "Restaurants are solely responsible for the service; availability and quality of the events including all or any cancellations/ modifications/ complaints.", "friendly_start_date": "02 March", "is_end_time_set": 1, "event_id": 110956, "end_date": "2017-06-30", "event_category": 0, "friendly_end_date": "30 June", "is_active": 1, "start_time": "16:00:00", "is_valid": 1, "event_category_name": ""}}, {"event": {"display_date": "02 March - 30 June", "end_time": "01:00:00", "date_added": "2017-03-02 19:47:30", "start_date": "2017-03-02", "photos": [{"photo": {"photo_id": 176935, "order": 0, "type": "NORMAL", "url": "https://b.zmtcdn.com/data/zomato_events/photos/ba9/c066ca8e5bc0aa81269a927297bd7ba9_1488464250.jpg", "md5sum": "c066ca8e5bc0aa81269a927297bd7ba9", "uuid": 1488464214491957, "thumb_url": "https://b.zmtcdn.com/data/zomato_events/photos/ba9/c066ca8e5bc0aa81269a927297bd7ba9_1488464250.jpg?fit=around%7C100%3A100&crop=100%3A100%3B%2A%2C%2A"}}], "share_url": "http://www.zoma.to/r/18222559", "description": "Music is an essence which behold your hearts and touches your soul. When you experience it for real than in your headphones is when your feet tap to the happiness in your heart! Niche brings to you Live music- because you cannot download a live musical experience.", "title": "Stirring some great cocktails and strumming some great beats!", "display_time": "07:00 pm - 01:00 am", "book_link": "", "restaurants": [], "disclaimer": "Restaurants are solely responsible for the service; availability and quality of the events including all or any cancellations/ modifications/ complaints.", "friendly_start_date": "02 March", "is_end_time_set": 1, "event_id": 110958, "end_date": "2017-06-30", "event_category": 0, "friendly_end_date": "30 June", "is_active": 1, "start_time": "19:00:00", "is_valid": 1, "event_category_name": ""}}], "currency": "Rs.", "id": "18222559", "thumb": "https://b.zmtcdn.com/data/pictures/9/18222559/f3b1c0e0901083619784bf0ba7c25996_featured_v2.jpg", "establishment_types": [], "events_url": "https://www.zomato.com/ncr/niche-cafe-bar-connaught-place-new-delhi/events#tabtop?utm_source=api_basic_user&utm_medium=api&utm_campaign=v2.1"}}